obsidian_cli/__init__.py
obsidian_cli/__main__.py
obsidian_cli/cli/__init__.py
obsidian_cli/cli/autocomplete.py
obsidian_cli/cli/templates.py
obsidian_cli/obsidian.py
obsidian_cli/py.typed
obsidian_cli/vault_templates.py
obsidian_cli-1.0.2.dist-info/WHEEL
obsidian_cli-1.0.2.dist-info/entry_points.txt
obsidian_cli-1.0.2.dist-info/METADATA
obsidian_cli-1.0.2.dist-info/RECORD
