Metadata-Version: 2.3
Name: obsidian-cli
Version: 1.0.2
Summary: Command line utility to interact with Obsidian, providing much needed features.
Author: Bip901
Author-email: Bip901 <74911767+Bip901@users.noreply.github.com>
Classifier: Topic :: Text Processing :: Markup :: Markdown
Classifier: Operating System :: OS Independent
Classifier: License :: OSI Approved :: MIT License
Classifier: Typing :: Typed
Classifier: Programming Language :: Python :: 3
Classifier: Programming Language :: Python :: 3 :: Only
Classifier: Programming Language :: Python :: 3.11
Classifier: Programming Language :: Python :: 3.12
Classifier: Programming Language :: Python :: 3.13
Requires-Dist: platformdirs>=4.4.0
Requires-Dist: pydantic>=2.11.7
Requires-Dist: tabulate>=0.9.0
Requires-Dist: typer>=0.17.4
Requires-Python: >=3.11
Project-URL: Homepage, https://github.com/Bip901/obsidian-cli
